cx/__init__.py
cx/cli.py
cx/clockwise.py
cx/main.py
cx/test.py
cx/view_vectors.py
cx-0.2.4.dist-info/entry_points.txt
cx-0.2.4.dist-info/licenses/LICENSE
cx-0.2.4.dist-info/WHEEL
cx-0.2.4.dist-info/METADATA
cx-0.2.4.dist-info/RECORD
