Metadata-Version: 2.4
Name: cx
Version: 0.2.4
Summary: Compute nearest neighbor distances along the coast with a view angle.
Home-page: https://github.com/bast/coastal-express
Author: Radovan Bast
Author-email: bast@users.noreply.github.com
Classifier: License :: OSI Approved :: Mozilla Public License 2.0 (MPL 2.0)
License-File: LICENSE
Requires-Dist: click
Requires-Dist: flanders==0.3.3
